mysqldbwrapper/__init__.py
mysqldbwrapper/base.py
django_mysqldbwrapper-0.3.dist-info/METADATA
django_mysqldbwrapper-0.3.dist-info/WHEEL
django_mysqldbwrapper-0.3.dist-info/top_level.txt
django_mysqldbwrapper-0.3.dist-info/RECORD
