Metadata-Version: 2.1
Name: django-mysqldbwrapper
Version: 0.3
Summary: state away mysql persistance connection
Home-page: https://halovina.com/project/open-library
Author: ALFIN
Author-email: alfin@halovina.com
License: open source
Platform: UNKNOWN
Requires-Dist: Django (>=4.0)
